amazon_textract_pipeline_pagedimensions-0.0.9.data/scripts/amazon-textract-pipeline-pagedimensions
textractpagedimensions/__init__.py
textractpagedimensions/_version.py
textractpagedimensions/t_pagedimensions.py
amazon_textract_pipeline_pagedimensions-0.0.9.dist-info/LICENSE
amazon_textract_pipeline_pagedimensions-0.0.9.dist-info/METADATA
amazon_textract_pipeline_pagedimensions-0.0.9.dist-info/WHEEL
amazon_textract_pipeline_pagedimensions-0.0.9.dist-info/top_level.txt
amazon_textract_pipeline_pagedimensions-0.0.9.dist-info/RECORD
