Metadata-Version: 2.1
Name: amazon-textract-pipeline-pagedimensions
Version: 0.0.9
Summary: Amazon Textract Pipeline Component to add page dimensions to page block types
Home-page: https://github.com/aws-samples/amazon-textract-textractor/tree/master/tpipelinepagedimensions
Author: Amazon Rekognition Textract Demoes
Author-email: rekognition-textract-demos@amazon.com
License: Apache License Version 2.0
Keywords: amazon-textract-textractor amazon textract textractor pipeline page dimensions
Platform: UNKNOWN
Classifier: Development Status :: 4 - Beta
Classifier: Topic :: Utilities
Classifier: License :: OSI Approved :: Apache Software License
Classifier: Programming Language :: Python :: 3.6
Classifier: Programming Language :: Python :: 3.7
Classifier: Programming Language :: Python :: 3.8
Classifier: Programming Language :: Python :: 3.9
Classifier: Programming Language :: Python :: 3.10
Requires-Python: >=3.6
Requires-Dist: boto3
Requires-Dist: botocore
Requires-Dist: Pillow (<9.5,>=9.4)
Requires-Dist: pypdf (<4.0,>=3.1)
